{
    "topic_types": [
        {
            "value": "HTML Template",
            "uri": "de.mikromedia.page.template",
            "dataTypeUri": "dmx.core.text",
            "viewConfigTopics": [
                {
                    "typeUri": "dmx.webclient.view_config",
                    "children": {
                        "dmx.webclient.add_to_create_menu": false
                    }
                }
            ]
        }
    ],
    "topics": [
        {
            "typeUri": "de.mikromedia.site.stylesheet",
            "uri" : "de.mikromedia.iass_promut_style",
            "value": "/de.mikromedia.webpages/static/css/promut.css"
        },
        {
            "typeUri": "de.mikromedia.page.template",
            "uri" : "de.mikromedia.template_page",
            "value": "Page"
        },
        {
            "typeUri": "de.mikromedia.page.template",
            "uri" : "de.mikromedia.template_collection",
            "value": "Collection"
        },
        {
            "typeUri": "de.mikromedia.page.template",
            "uri" : "de.mikromedia.template_post",
            "value": "Post"
        }
    ]
}
